[
    {
        "status": "down",
        "timestamp": "2026-03-14 15:55:15"
    },
    {
        "status": "down",
        "timestamp": "2026-03-14 16:21:54"
    },
    {
        "status": "down",
        "timestamp": "2026-03-14 16:53:58"
    },
    {
        "status": "down",
        "timestamp": "2026-03-14 17:20:13"
    },
    {
        "status": "down",
        "timestamp": "2026-03-14 17:46:54"
    },
    {
        "status": "down",
        "timestamp": "2026-03-14 18:00:30"
    },
    {
        "status": "down",
        "timestamp": "2026-03-14 18:54:34"
    },
    {
        "status": "down",
        "timestamp": "2026-03-14 19:21:10"
    },
    {
        "status": "down",
        "timestamp": "2026-03-14 19:46:12"
    },
    {
        "status": "down",
        "timestamp": "2026-03-14 19:58:49"
    },
    {
        "status": "down",
        "timestamp": "2026-03-14 20:31:53"
    },
    {
        "status": "down",
        "timestamp": "2026-03-14 20:56:33"
    },
    {
        "status": "down",
        "timestamp": "2026-03-14 21:22:45"
    },
    {
        "status": "down",
        "timestamp": "2026-03-14 21:46:37"
    },
    {
        "status": "down",
        "timestamp": "2026-03-14 21:59:42"
    },
    {
        "status": "down",
        "timestamp": "2026-03-14 22:31:43"
    },
    {
        "status": "down",
        "timestamp": "2026-03-14 22:56:25"
    },
    {
        "status": "down",
        "timestamp": "2026-03-14 23:23:43"
    },
    {
        "status": "down",
        "timestamp": "2026-03-14 23:48:10"
    },
    {
        "status": "down",
        "timestamp": "2026-03-15 00:01:23"
    },
    {
        "status": "down",
        "timestamp": "2026-03-15 03:27:53"
    },
    {
        "status": "down",
        "timestamp": "2026-03-15 05:16:29"
    },
    {
        "status": "down",
        "timestamp": "2026-03-15 06:11:48"
    },
    {
        "status": "down",
        "timestamp": "2026-03-15 07:14:02"
    },
    {
        "status": "down",
        "timestamp": "2026-03-15 07:53:05"
    },
    {
        "status": "down",
        "timestamp": "2026-03-15 08:28:36"
    },
    {
        "status": "down",
        "timestamp": "2026-03-15 09:01:44"
    },
    {
        "status": "down",
        "timestamp": "2026-03-15 09:46:28"
    },
    {
        "status": "down",
        "timestamp": "2026-03-15 10:02:17"
    },
    {
        "status": "down",
        "timestamp": "2026-03-15 10:46:21"
    }
]