[
    {
        "status": "down",
        "timestamp": "2025-07-14 09:47:19"
    },
    {
        "status": "down",
        "timestamp": "2025-07-14 09:58:11"
    },
    {
        "status": "down",
        "timestamp": "2025-07-14 10:23:51"
    },
    {
        "status": "down",
        "timestamp": "2025-07-14 10:46:36"
    },
    {
        "status": "down",
        "timestamp": "2025-07-14 10:57:21"
    },
    {
        "status": "down",
        "timestamp": "2025-07-14 11:16:40"
    },
    {
        "status": "down",
        "timestamp": "2025-07-14 11:31:37"
    },
    {
        "status": "down",
        "timestamp": "2025-07-14 11:45:14"
    },
    {
        "status": "down",
        "timestamp": "2025-07-14 11:52:50"
    },
    {
        "status": "down",
        "timestamp": "2025-07-14 12:28:28"
    },
    {
        "status": "down",
        "timestamp": "2025-07-14 13:10:37"
    },
    {
        "status": "down",
        "timestamp": "2025-07-14 13:48:46"
    },
    {
        "status": "down",
        "timestamp": "2025-07-14 13:59:32"
    },
    {
        "status": "down",
        "timestamp": "2025-07-14 14:25:27"
    },
    {
        "status": "down",
        "timestamp": "2025-07-14 14:45:06"
    },
    {
        "status": "down",
        "timestamp": "2025-07-14 14:56:06"
    },
    {
        "status": "down",
        "timestamp": "2025-07-14 15:17:31"
    },
    {
        "status": "down",
        "timestamp": "2025-07-14 15:39:33"
    },
    {
        "status": "down",
        "timestamp": "2025-07-14 15:52:16"
    },
    {
        "status": "down",
        "timestamp": "2025-07-14 16:17:43"
    },
    {
        "status": "down",
        "timestamp": "2025-07-14 16:45:35"
    },
    {
        "status": "down",
        "timestamp": "2025-07-14 16:59:49"
    },
    {
        "status": "down",
        "timestamp": "2025-07-14 17:23:30"
    },
    {
        "status": "down",
        "timestamp": "2025-07-14 17:42:46"
    },
    {
        "status": "down",
        "timestamp": "2025-07-14 17:53:39"
    },
    {
        "status": "down",
        "timestamp": "2025-07-14 18:20:40"
    },
    {
        "status": "down",
        "timestamp": "2025-07-14 18:52:23"
    },
    {
        "status": "down",
        "timestamp": "2025-07-14 19:11:41"
    },
    {
        "status": "down",
        "timestamp": "2025-07-14 19:29:35"
    },
    {
        "status": "down",
        "timestamp": "2025-07-14 19:41:03"
    }
]