[
    {
        "status": "down",
        "timestamp": "2026-01-25 23:33:24"
    },
    {
        "status": "down",
        "timestamp": "2026-01-25 23:47:15"
    },
    {
        "status": "down",
        "timestamp": "2026-01-25 23:54:57"
    },
    {
        "status": "down",
        "timestamp": "2026-01-26 01:16:19"
    },
    {
        "status": "down",
        "timestamp": "2026-01-26 03:24:26"
    },
    {
        "status": "down",
        "timestamp": "2026-01-26 04:38:04"
    },
    {
        "status": "down",
        "timestamp": "2026-01-26 05:19:09"
    },
    {
        "status": "down",
        "timestamp": "2026-01-26 05:50:01"
    },
    {
        "status": "down",
        "timestamp": "2026-01-26 06:01:06"
    },
    {
        "status": "down",
        "timestamp": "2026-01-26 06:53:35"
    },
    {
        "status": "down",
        "timestamp": "2026-01-26 07:22:00"
    },
    {
        "status": "down",
        "timestamp": "2026-01-26 07:45:38"
    },
    {
        "status": "down",
        "timestamp": "2026-01-26 07:56:16"
    },
    {
        "status": "down",
        "timestamp": "2026-01-26 08:27:01"
    },
    {
        "status": "down",
        "timestamp": "2026-01-26 08:56:59"
    },
    {
        "status": "down",
        "timestamp": "2026-01-26 09:31:59"
    },
    {
        "status": "down",
        "timestamp": "2026-01-26 09:58:16"
    },
    {
        "status": "down",
        "timestamp": "2026-01-26 10:28:44"
    },
    {
        "status": "down",
        "timestamp": "2026-01-26 10:52:33"
    },
    {
        "status": "down",
        "timestamp": "2026-01-26 11:16:00"
    },
    {
        "status": "down",
        "timestamp": "2026-01-26 11:34:15"
    },
    {
        "status": "down",
        "timestamp": "2026-01-26 11:47:19"
    },
    {
        "status": "down",
        "timestamp": "2026-01-26 11:55:26"
    },
    {
        "status": "down",
        "timestamp": "2026-01-26 12:33:55"
    },
    {
        "status": "down",
        "timestamp": "2026-01-26 13:28:44"
    },
    {
        "status": "down",
        "timestamp": "2026-01-26 13:59:32"
    },
    {
        "status": "down",
        "timestamp": "2026-01-26 14:33:31"
    },
    {
        "status": "down",
        "timestamp": "2026-01-26 14:58:10"
    },
    {
        "status": "down",
        "timestamp": "2026-01-26 15:29:55"
    },
    {
        "status": "down",
        "timestamp": "2026-01-26 15:53:37"
    }
]