[
    {
        "status": "down",
        "timestamp": "2025-08-12 15:15:31"
    },
    {
        "status": "down",
        "timestamp": "2025-08-12 15:37:26"
    },
    {
        "status": "down",
        "timestamp": "2025-08-12 15:50:35"
    },
    {
        "status": "down",
        "timestamp": "2025-08-12 16:17:13"
    },
    {
        "status": "down",
        "timestamp": "2025-08-12 16:44:37"
    },
    {
        "status": "down",
        "timestamp": "2025-08-12 16:59:11"
    },
    {
        "status": "down",
        "timestamp": "2025-08-12 17:21:32"
    },
    {
        "status": "down",
        "timestamp": "2025-08-12 17:41:25"
    },
    {
        "status": "down",
        "timestamp": "2025-08-12 17:53:27"
    },
    {
        "status": "down",
        "timestamp": "2025-08-12 18:20:40"
    },
    {
        "status": "down",
        "timestamp": "2025-08-12 18:50:37"
    },
    {
        "status": "down",
        "timestamp": "2025-08-12 19:11:26"
    },
    {
        "status": "down",
        "timestamp": "2025-08-12 19:28:22"
    },
    {
        "status": "down",
        "timestamp": "2025-08-12 19:38:34"
    },
    {
        "status": "down",
        "timestamp": "2025-08-12 19:46:11"
    },
    {
        "status": "down",
        "timestamp": "2025-08-12 19:53:48"
    },
    {
        "status": "down",
        "timestamp": "2025-08-12 20:15:18"
    },
    {
        "status": "down",
        "timestamp": "2025-08-12 20:36:31"
    },
    {
        "status": "down",
        "timestamp": "2025-08-12 20:49:16"
    },
    {
        "status": "down",
        "timestamp": "2025-08-12 20:56:45"
    },
    {
        "status": "down",
        "timestamp": "2025-08-12 21:16:14"
    },
    {
        "status": "down",
        "timestamp": "2025-08-12 21:32:44"
    },
    {
        "status": "down",
        "timestamp": "2025-08-12 21:45:20"
    },
    {
        "status": "down",
        "timestamp": "2025-08-12 21:52:59"
    },
    {
        "status": "down",
        "timestamp": "2025-08-12 22:12:49"
    },
    {
        "status": "down",
        "timestamp": "2025-08-12 22:35:24"
    },
    {
        "status": "down",
        "timestamp": "2025-08-12 22:47:50"
    },
    {
        "status": "down",
        "timestamp": "2025-08-12 22:55:18"
    },
    {
        "status": "down",
        "timestamp": "2025-08-12 23:13:21"
    },
    {
        "status": "down",
        "timestamp": "2025-08-12 23:31:26"
    }
]