[
    {
        "status": "up",
        "timestamp": "2025-01-26 03:43:25"
    },
    {
        "status": "up",
        "timestamp": "2025-01-26 03:53:03"
    },
    {
        "status": "up",
        "timestamp": "2025-01-26 04:12:47"
    },
    {
        "status": "up",
        "timestamp": "2025-01-26 04:31:26"
    },
    {
        "status": "up",
        "timestamp": "2025-01-26 04:42:49"
    },
    {
        "status": "up",
        "timestamp": "2025-01-26 04:52:34"
    },
    {
        "status": "up",
        "timestamp": "2025-01-26 05:11:39"
    },
    {
        "status": "up",
        "timestamp": "2025-01-26 05:30:25"
    },
    {
        "status": "up",
        "timestamp": "2025-01-26 05:42:54"
    },
    {
        "status": "up",
        "timestamp": "2025-01-26 05:52:51"
    },
    {
        "status": "up",
        "timestamp": "2025-01-26 06:14:25"
    },
    {
        "status": "up",
        "timestamp": "2025-01-26 06:33:57"
    },
    {
        "status": "up",
        "timestamp": "2025-01-26 06:44:17"
    },
    {
        "status": "up",
        "timestamp": "2025-01-26 06:52:34"
    },
    {
        "status": "up",
        "timestamp": "2025-01-26 07:09:43"
    },
    {
        "status": "up",
        "timestamp": "2025-01-26 07:22:31"
    },
    {
        "status": "up",
        "timestamp": "2025-01-26 07:34:08"
    },
    {
        "status": "up",
        "timestamp": "2025-01-26 07:42:44"
    },
    {
        "status": "up",
        "timestamp": "2025-01-26 07:53:04"
    },
    {
        "status": "up",
        "timestamp": "2025-01-26 08:12:42"
    },
    {
        "status": "up",
        "timestamp": "2025-01-26 08:29:52"
    },
    {
        "status": "up",
        "timestamp": "2025-01-26 08:39:15"
    },
    {
        "status": "up",
        "timestamp": "2025-01-26 08:47:01"
    },
    {
        "status": "up",
        "timestamp": "2025-01-26 08:54:39"
    },
    {
        "status": "up",
        "timestamp": "2025-01-26 09:10:39"
    },
    {
        "status": "up",
        "timestamp": "2025-01-26 09:26:55"
    },
    {
        "status": "up",
        "timestamp": "2025-01-26 09:35:10"
    },
    {
        "status": "up",
        "timestamp": "2025-01-26 09:42:37"
    },
    {
        "status": "up",
        "timestamp": "2025-01-26 09:53:06"
    },
    {
        "status": "up",
        "timestamp": "2025-01-26 10:11:05"
    }
]