[
    {
        "status": "down",
        "timestamp": "2025-11-18 13:07:38"
    },
    {
        "status": "down",
        "timestamp": "2025-11-18 13:40:40"
    },
    {
        "status": "down",
        "timestamp": "2025-11-18 13:54:53"
    },
    {
        "status": "down",
        "timestamp": "2025-11-18 14:13:23"
    },
    {
        "status": "down",
        "timestamp": "2025-11-18 14:37:31"
    },
    {
        "status": "down",
        "timestamp": "2025-11-18 14:50:41"
    },
    {
        "status": "down",
        "timestamp": "2025-11-18 15:15:06"
    },
    {
        "status": "down",
        "timestamp": "2025-11-18 15:37:25"
    },
    {
        "status": "down",
        "timestamp": "2025-11-18 15:50:13"
    },
    {
        "status": "down",
        "timestamp": "2025-11-18 16:18:26"
    },
    {
        "status": "down",
        "timestamp": "2025-11-18 16:46:27"
    },
    {
        "status": "down",
        "timestamp": "2025-11-18 16:59:48"
    },
    {
        "status": "down",
        "timestamp": "2025-11-18 17:22:54"
    },
    {
        "status": "down",
        "timestamp": "2025-11-18 17:39:59"
    },
    {
        "status": "down",
        "timestamp": "2025-11-18 17:48:53"
    },
    {
        "status": "down",
        "timestamp": "2025-11-18 17:56:40"
    },
    {
        "status": "down",
        "timestamp": "2025-11-18 18:25:50"
    },
    {
        "status": "down",
        "timestamp": "2025-11-18 18:50:04"
    },
    {
        "status": "down",
        "timestamp": "2025-11-18 18:59:39"
    },
    {
        "status": "down",
        "timestamp": "2025-11-18 19:19:17"
    },
    {
        "status": "down",
        "timestamp": "2025-11-18 19:27:56"
    },
    {
        "status": "down",
        "timestamp": "2025-11-18 19:36:46"
    },
    {
        "status": "down",
        "timestamp": "2025-11-18 19:44:20"
    },
    {
        "status": "down",
        "timestamp": "2025-11-18 19:52:55"
    },
    {
        "status": "down",
        "timestamp": "2025-11-18 20:16:16"
    },
    {
        "status": "down",
        "timestamp": "2025-11-18 21:46:04"
    },
    {
        "status": "down",
        "timestamp": "2025-11-18 21:53:51"
    },
    {
        "status": "down",
        "timestamp": "2025-11-18 22:12:59"
    },
    {
        "status": "down",
        "timestamp": "2025-11-18 22:34:25"
    },
    {
        "status": "down",
        "timestamp": "2025-11-18 22:45:55"
    }
]