[
    {
        "status": "down",
        "timestamp": "2026-02-22 06:25:09"
    },
    {
        "status": "down",
        "timestamp": "2026-02-22 07:09:38"
    },
    {
        "status": "down",
        "timestamp": "2026-02-22 07:47:30"
    },
    {
        "status": "down",
        "timestamp": "2026-02-22 08:00:09"
    },
    {
        "status": "down",
        "timestamp": "2026-02-22 08:40:24"
    },
    {
        "status": "down",
        "timestamp": "2026-02-22 09:03:51"
    },
    {
        "status": "down",
        "timestamp": "2026-02-22 09:42:25"
    },
    {
        "status": "down",
        "timestamp": "2026-02-22 09:59:22"
    },
    {
        "status": "down",
        "timestamp": "2026-02-22 10:29:48"
    },
    {
        "status": "down",
        "timestamp": "2026-02-22 10:53:07"
    },
    {
        "status": "down",
        "timestamp": "2026-02-22 11:15:34"
    },
    {
        "status": "down",
        "timestamp": "2026-02-22 11:35:54"
    },
    {
        "status": "down",
        "timestamp": "2026-02-22 11:50:05"
    },
    {
        "status": "down",
        "timestamp": "2026-02-22 11:58:31"
    },
    {
        "status": "down",
        "timestamp": "2026-02-22 12:54:04"
    },
    {
        "status": "down",
        "timestamp": "2026-02-22 13:38:07"
    },
    {
        "status": "down",
        "timestamp": "2026-02-22 14:02:18"
    },
    {
        "status": "down",
        "timestamp": "2026-02-22 14:39:02"
    },
    {
        "status": "down",
        "timestamp": "2026-02-22 14:57:09"
    },
    {
        "status": "down",
        "timestamp": "2026-02-22 15:22:25"
    },
    {
        "status": "down",
        "timestamp": "2026-02-22 15:46:28"
    },
    {
        "status": "down",
        "timestamp": "2026-02-22 16:00:11"
    },
    {
        "status": "down",
        "timestamp": "2026-02-22 16:38:36"
    },
    {
        "status": "down",
        "timestamp": "2026-02-22 17:00:01"
    },
    {
        "status": "down",
        "timestamp": "2026-02-22 17:30:41"
    },
    {
        "status": "down",
        "timestamp": "2026-02-22 17:53:48"
    },
    {
        "status": "down",
        "timestamp": "2026-02-22 18:25:24"
    },
    {
        "status": "down",
        "timestamp": "2026-02-22 18:59:00"
    },
    {
        "status": "down",
        "timestamp": "2026-02-22 19:28:11"
    },
    {
        "status": "down",
        "timestamp": "2026-02-22 19:46:20"
    }
]