[
    {
        "status": "down",
        "timestamp": "2025-09-04 07:37:11"
    },
    {
        "status": "down",
        "timestamp": "2025-09-04 07:44:38"
    },
    {
        "status": "down",
        "timestamp": "2025-09-04 07:52:52"
    },
    {
        "status": "down",
        "timestamp": "2025-09-04 08:16:48"
    },
    {
        "status": "down",
        "timestamp": "2025-09-04 08:39:10"
    },
    {
        "status": "down",
        "timestamp": "2025-09-04 08:51:52"
    },
    {
        "status": "down",
        "timestamp": "2025-09-04 09:13:35"
    },
    {
        "status": "down",
        "timestamp": "2025-09-04 09:31:10"
    },
    {
        "status": "down",
        "timestamp": "2025-09-04 09:43:18"
    },
    {
        "status": "down",
        "timestamp": "2025-09-04 09:52:32"
    },
    {
        "status": "down",
        "timestamp": "2025-09-04 10:13:05"
    },
    {
        "status": "down",
        "timestamp": "2025-09-04 10:34:05"
    },
    {
        "status": "down",
        "timestamp": "2025-09-04 10:44:59"
    },
    {
        "status": "down",
        "timestamp": "2025-09-04 10:52:49"
    },
    {
        "status": "down",
        "timestamp": "2025-09-04 11:10:12"
    },
    {
        "status": "down",
        "timestamp": "2025-09-04 11:26:33"
    },
    {
        "status": "down",
        "timestamp": "2025-09-04 11:35:45"
    },
    {
        "status": "down",
        "timestamp": "2025-09-04 11:43:16"
    },
    {
        "status": "down",
        "timestamp": "2025-09-04 11:52:55"
    },
    {
        "status": "down",
        "timestamp": "2025-09-04 12:25:39"
    },
    {
        "status": "down",
        "timestamp": "2025-09-04 12:59:58"
    },
    {
        "status": "down",
        "timestamp": "2025-09-04 13:30:09"
    },
    {
        "status": "down",
        "timestamp": "2025-09-04 13:43:18"
    },
    {
        "status": "down",
        "timestamp": "2025-09-04 13:53:05"
    },
    {
        "status": "down",
        "timestamp": "2025-09-04 14:12:07"
    },
    {
        "status": "down",
        "timestamp": "2025-09-04 14:34:19"
    },
    {
        "status": "down",
        "timestamp": "2025-09-04 14:45:58"
    },
    {
        "status": "down",
        "timestamp": "2025-09-04 14:53:41"
    },
    {
        "status": "down",
        "timestamp": "2025-09-04 15:13:09"
    },
    {
        "status": "down",
        "timestamp": "2025-09-04 15:31:39"
    }
]