[
    {
        "status": "up",
        "timestamp": "2025-04-29 09:36:52"
    },
    {
        "status": "up",
        "timestamp": "2025-04-29 09:47:28"
    },
    {
        "status": "up",
        "timestamp": "2025-04-29 09:54:48"
    },
    {
        "status": "up",
        "timestamp": "2025-04-29 10:14:30"
    },
    {
        "status": "up",
        "timestamp": "2025-04-29 10:40:47"
    },
    {
        "status": "up",
        "timestamp": "2025-04-29 10:53:21"
    },
    {
        "status": "up",
        "timestamp": "2025-04-29 11:11:01"
    },
    {
        "status": "up",
        "timestamp": "2025-04-29 11:28:03"
    },
    {
        "status": "up",
        "timestamp": "2025-04-29 11:37:40"
    },
    {
        "status": "up",
        "timestamp": "2025-04-29 11:45:16"
    },
    {
        "status": "up",
        "timestamp": "2025-04-29 11:52:58"
    },
    {
        "status": "up",
        "timestamp": "2025-04-29 12:26:31"
    },
    {
        "status": "up",
        "timestamp": "2025-04-29 13:07:24"
    },
    {
        "status": "up",
        "timestamp": "2025-04-29 13:41:27"
    },
    {
        "status": "up",
        "timestamp": "2025-04-29 13:55:30"
    },
    {
        "status": "up",
        "timestamp": "2025-04-29 14:14:00"
    },
    {
        "status": "up",
        "timestamp": "2025-04-29 14:36:57"
    },
    {
        "status": "up",
        "timestamp": "2025-04-29 14:49:08"
    },
    {
        "status": "up",
        "timestamp": "2025-04-29 14:56:32"
    },
    {
        "status": "up",
        "timestamp": "2025-04-29 15:16:52"
    },
    {
        "status": "up",
        "timestamp": "2025-04-29 15:34:39"
    },
    {
        "status": "up",
        "timestamp": "2025-04-29 15:46:21"
    },
    {
        "status": "up",
        "timestamp": "2025-04-29 15:54:01"
    },
    {
        "status": "up",
        "timestamp": "2025-04-29 16:15:35"
    },
    {
        "status": "up",
        "timestamp": "2025-04-29 16:41:10"
    },
    {
        "status": "up",
        "timestamp": "2025-04-29 16:55:28"
    },
    {
        "status": "up",
        "timestamp": "2025-04-29 17:12:28"
    },
    {
        "status": "up",
        "timestamp": "2025-04-29 17:32:22"
    },
    {
        "status": "up",
        "timestamp": "2025-04-29 17:44:06"
    },
    {
        "status": "up",
        "timestamp": "2025-04-29 17:52:44"
    }
]