[
    {
        "status": "up",
        "timestamp": "2025-06-16 22:47:35"
    },
    {
        "status": "up",
        "timestamp": "2025-06-16 22:55:17"
    },
    {
        "status": "up",
        "timestamp": "2025-06-16 23:12:36"
    },
    {
        "status": "up",
        "timestamp": "2025-06-16 23:30:59"
    },
    {
        "status": "up",
        "timestamp": "2025-06-16 23:44:46"
    },
    {
        "status": "up",
        "timestamp": "2025-06-16 23:52:55"
    },
    {
        "status": "up",
        "timestamp": "2025-06-17 01:05:30"
    },
    {
        "status": "up",
        "timestamp": "2025-06-17 02:53:07"
    },
    {
        "status": "up",
        "timestamp": "2025-06-17 03:44:04"
    },
    {
        "status": "up",
        "timestamp": "2025-06-17 04:16:05"
    },
    {
        "status": "up",
        "timestamp": "2025-06-17 04:43:35"
    },
    {
        "status": "up",
        "timestamp": "2025-06-17 04:56:38"
    },
    {
        "status": "up",
        "timestamp": "2025-06-17 05:16:35"
    },
    {
        "status": "up",
        "timestamp": "2025-06-17 05:37:28"
    },
    {
        "status": "up",
        "timestamp": "2025-06-17 05:48:59"
    },
    {
        "status": "up",
        "timestamp": "2025-06-17 05:56:38"
    },
    {
        "status": "up",
        "timestamp": "2025-06-17 06:24:40"
    },
    {
        "status": "up",
        "timestamp": "2025-06-17 06:49:47"
    },
    {
        "status": "up",
        "timestamp": "2025-06-17 06:59:36"
    },
    {
        "status": "up",
        "timestamp": "2025-06-17 07:22:55"
    },
    {
        "status": "up",
        "timestamp": "2025-06-17 07:39:49"
    },
    {
        "status": "up",
        "timestamp": "2025-06-17 07:48:50"
    },
    {
        "status": "up",
        "timestamp": "2025-06-17 07:56:21"
    },
    {
        "status": "up",
        "timestamp": "2025-06-17 08:22:17"
    },
    {
        "status": "up",
        "timestamp": "2025-06-17 08:47:24"
    },
    {
        "status": "up",
        "timestamp": "2025-06-17 08:59:54"
    },
    {
        "status": "up",
        "timestamp": "2025-06-17 09:27:08"
    },
    {
        "status": "up",
        "timestamp": "2025-06-17 09:43:11"
    },
    {
        "status": "up",
        "timestamp": "2025-06-17 09:53:37"
    },
    {
        "status": "up",
        "timestamp": "2025-06-17 10:14:28"
    }
]