[
    {
        "status": "down",
        "timestamp": "2025-06-06 15:32:23"
    },
    {
        "status": "down",
        "timestamp": "2025-06-06 15:45:09"
    },
    {
        "status": "down",
        "timestamp": "2025-06-06 15:52:53"
    },
    {
        "status": "down",
        "timestamp": "2025-06-06 16:16:48"
    },
    {
        "status": "down",
        "timestamp": "2025-06-06 16:43:37"
    },
    {
        "status": "down",
        "timestamp": "2025-06-06 16:57:12"
    },
    {
        "status": "down",
        "timestamp": "2025-06-06 17:16:13"
    },
    {
        "status": "down",
        "timestamp": "2025-06-06 17:34:33"
    },
    {
        "status": "down",
        "timestamp": "2025-06-06 17:46:03"
    },
    {
        "status": "down",
        "timestamp": "2025-06-06 17:53:37"
    },
    {
        "status": "down",
        "timestamp": "2025-06-06 18:18:30"
    },
    {
        "status": "down",
        "timestamp": "2025-06-06 18:44:33"
    },
    {
        "status": "down",
        "timestamp": "2025-06-06 18:56:18"
    },
    {
        "status": "down",
        "timestamp": "2025-06-06 19:12:37"
    },
    {
        "status": "down",
        "timestamp": "2025-06-06 19:27:36"
    },
    {
        "status": "down",
        "timestamp": "2025-06-06 19:36:49"
    },
    {
        "status": "down",
        "timestamp": "2025-06-06 19:44:21"
    },
    {
        "status": "down",
        "timestamp": "2025-06-06 19:52:57"
    },
    {
        "status": "down",
        "timestamp": "2025-06-06 20:15:03"
    },
    {
        "status": "down",
        "timestamp": "2025-06-06 20:34:25"
    },
    {
        "status": "down",
        "timestamp": "2025-06-06 20:47:07"
    },
    {
        "status": "down",
        "timestamp": "2025-06-06 20:54:36"
    },
    {
        "status": "down",
        "timestamp": "2025-06-06 21:12:04"
    },
    {
        "status": "down",
        "timestamp": "2025-06-06 21:30:47"
    },
    {
        "status": "down",
        "timestamp": "2025-06-06 21:43:34"
    },
    {
        "status": "down",
        "timestamp": "2025-06-06 21:52:47"
    },
    {
        "status": "down",
        "timestamp": "2025-06-06 22:12:17"
    },
    {
        "status": "down",
        "timestamp": "2025-06-06 22:35:48"
    },
    {
        "status": "down",
        "timestamp": "2025-06-06 22:45:13"
    },
    {
        "status": "down",
        "timestamp": "2025-06-06 22:52:40"
    }
]