[
    {
        "status": "down",
        "timestamp": "2025-10-15 11:53:02"
    },
    {
        "status": "down",
        "timestamp": "2025-10-15 12:27:55"
    },
    {
        "status": "down",
        "timestamp": "2025-10-15 13:06:51"
    },
    {
        "status": "down",
        "timestamp": "2025-10-15 13:39:28"
    },
    {
        "status": "down",
        "timestamp": "2025-10-15 13:51:23"
    },
    {
        "status": "down",
        "timestamp": "2025-10-15 14:13:38"
    },
    {
        "status": "down",
        "timestamp": "2025-10-15 14:38:43"
    },
    {
        "status": "down",
        "timestamp": "2025-10-15 14:50:48"
    },
    {
        "status": "down",
        "timestamp": "2025-10-15 15:13:07"
    },
    {
        "status": "down",
        "timestamp": "2025-10-15 15:30:39"
    },
    {
        "status": "down",
        "timestamp": "2025-10-15 15:45:05"
    },
    {
        "status": "down",
        "timestamp": "2025-10-15 15:53:11"
    },
    {
        "status": "down",
        "timestamp": "2025-10-15 16:13:47"
    },
    {
        "status": "down",
        "timestamp": "2025-10-15 16:36:56"
    },
    {
        "status": "down",
        "timestamp": "2025-10-15 16:49:31"
    },
    {
        "status": "down",
        "timestamp": "2025-10-15 16:57:05"
    },
    {
        "status": "down",
        "timestamp": "2025-10-15 17:15:38"
    },
    {
        "status": "down",
        "timestamp": "2025-10-15 17:30:57"
    },
    {
        "status": "down",
        "timestamp": "2025-10-15 17:43:41"
    },
    {
        "status": "down",
        "timestamp": "2025-10-15 17:52:59"
    },
    {
        "status": "down",
        "timestamp": "2025-10-15 18:19:18"
    },
    {
        "status": "down",
        "timestamp": "2025-10-15 18:44:21"
    },
    {
        "status": "down",
        "timestamp": "2025-10-15 18:55:19"
    },
    {
        "status": "down",
        "timestamp": "2025-10-15 19:11:00"
    },
    {
        "status": "down",
        "timestamp": "2025-10-15 19:26:08"
    },
    {
        "status": "down",
        "timestamp": "2025-10-15 19:35:41"
    },
    {
        "status": "down",
        "timestamp": "2025-10-15 19:43:10"
    },
    {
        "status": "down",
        "timestamp": "2025-10-15 19:52:33"
    },
    {
        "status": "down",
        "timestamp": "2025-10-15 20:14:35"
    },
    {
        "status": "down",
        "timestamp": "2025-10-15 20:33:49"
    }
]