[
    {
        "status": "up",
        "timestamp": "2025-05-11 17:38:37"
    },
    {
        "status": "up",
        "timestamp": "2025-05-11 17:46:10"
    },
    {
        "status": "up",
        "timestamp": "2025-05-11 17:53:44"
    },
    {
        "status": "up",
        "timestamp": "2025-05-11 18:15:45"
    },
    {
        "status": "up",
        "timestamp": "2025-05-11 18:38:41"
    },
    {
        "status": "up",
        "timestamp": "2025-05-11 18:49:27"
    },
    {
        "status": "up",
        "timestamp": "2025-05-11 18:57:05"
    },
    {
        "status": "up",
        "timestamp": "2025-05-11 19:12:31"
    },
    {
        "status": "up",
        "timestamp": "2025-05-11 19:25:06"
    },
    {
        "status": "up",
        "timestamp": "2025-05-11 19:34:09"
    },
    {
        "status": "up",
        "timestamp": "2025-05-11 19:43:02"
    },
    {
        "status": "up",
        "timestamp": "2025-05-11 19:52:37"
    },
    {
        "status": "up",
        "timestamp": "2025-05-11 20:12:47"
    },
    {
        "status": "up",
        "timestamp": "2025-05-11 20:31:04"
    },
    {
        "status": "up",
        "timestamp": "2025-05-11 20:43:29"
    },
    {
        "status": "up",
        "timestamp": "2025-05-11 20:52:53"
    },
    {
        "status": "up",
        "timestamp": "2025-05-11 21:10:56"
    },
    {
        "status": "up",
        "timestamp": "2025-05-11 21:28:19"
    },
    {
        "status": "up",
        "timestamp": "2025-05-11 21:37:17"
    },
    {
        "status": "up",
        "timestamp": "2025-05-11 21:44:55"
    },
    {
        "status": "up",
        "timestamp": "2025-05-11 21:52:46"
    },
    {
        "status": "up",
        "timestamp": "2025-05-11 22:11:23"
    },
    {
        "status": "up",
        "timestamp": "2025-05-11 22:33:09"
    },
    {
        "status": "up",
        "timestamp": "2025-05-11 22:44:11"
    },
    {
        "status": "up",
        "timestamp": "2025-05-11 22:52:59"
    },
    {
        "status": "up",
        "timestamp": "2025-05-11 23:11:38"
    },
    {
        "status": "up",
        "timestamp": "2025-05-11 23:29:03"
    },
    {
        "status": "up",
        "timestamp": "2025-05-11 23:39:12"
    },
    {
        "status": "up",
        "timestamp": "2025-05-11 23:46:40"
    },
    {
        "status": "up",
        "timestamp": "2025-05-11 23:54:26"
    }
]